LICENSE
MANIFEST.in
README.md
setup.cfg
setup.py
tsprocess/__init__.py
tsprocess/database.py
tsprocess/db_tracker.py
tsprocess/incident.py
tsprocess/log.py
tsprocess/project.py
tsprocess/record.py
tsprocess/seismicsource.py
tsprocess/station.py
tsprocess/timeseries.py
tsprocess/ts_plot_utils.py
tsprocess/ts_utils.py
tsprocess.egg-info/PKG-INFO
tsprocess.egg-info/SOURCES.txt
tsprocess.egg-info/dependency_links.txt
tsprocess.egg-info/top_level.txt