Metadata-Version: 2.1
Name: tsprocess
Version: 0.0.2
Summary: Ground motion time series processing tools
Home-page: https://github.com/Naeemkh/ts-process
Author: Naeem Khoshnevis
Author-email: khoshnevis.naeem@gmail.com
Maintainer: Naeem Khoshnevis, Fabio Silva, Ricardo Taborda, Christine Goulet
Maintainer-email: khoshnevis.naeem@gmail.com,fsilva@usc.edu, rtaborda@eafit.edu.co,cgoulet@usc.edu
License: BSD 3-Clause
Platform: UNKNOWN
Classifier: Development Status :: 2 - Pre-Alpha
Classifier: Intended Audience :: Science/Research
Classifier: License :: OSI Approved :: BSD License
Classifier: Natural Language :: English
Classifier: Operating System :: OS Independent
Classifier: Programming Language :: Python :: 3 :: Only
Classifier: Programming Language :: Python :: 3.7
Classifier: Programming Language :: Python :: 3.8
Classifier: Programming Language :: Python :: Implementation :: CPython
Classifier: Programming Language :: Python :: Implementation :: PyPy
Requires-Python: >=3.7
